omikb/__init__.py
omikb/domekb.py
omikb/omikb.py
test/__init__.py
test/test.py
omikb-0.0.2.dist-info/LICENSE
omikb-0.0.2.dist-info/METADATA
omikb-0.0.2.dist-info/WHEEL
omikb-0.0.2.dist-info/top_level.txt
omikb-0.0.2.dist-info/RECORD
