Metadata-Version: 2.1
Name: omikb
Version: 0.0.2
Summary: A set of methods to manage the OpenModel Knowledge Base Management
Home-page: https://github.com/H2020-OpenModel/OMIKB-toolbox/
Author: 'Materials Discovery Group (UCL)
Author-email: a.hashibon@ucl.ac.uk
Classifier: Programming Language :: Python :: 3
Classifier: License :: OSI Approved :: GNU General Public License v3 (GPLv3)
Classifier: Operating System :: OS Independent
Requires-Python: >=3.6
License-File: LICENSE
Requires-Dist: requests
Requires-Dist: rdflib
